{
  "instrument_id": 55,
  "instrument_acronym": "ATSR",
  "instrument_fullname": "Along-Track Scanning Radiometer",
  "url": "https://space.oscar.wmo.int/instruments/view/atsr",
  "schema_type": "microwave",
  "original_columns": [
    "Central wavelength/frequency",
    "Bandwidth",
    "SNR or NEΔT @ specified input"
  ],
  "channels": [
    {
      "channel_name": "Band_01",
      "central_frequency": {
        "value": 1.61,
        "unit": "µm"
      },
      "bandwidth": {
        "min": 1.46,
        "max": 1.76,
        "unit": "µm"
      },
      "SNR or NEΔT @ specified input": "20 @ 0.5 % albedo"
    },
    {
      "channel_name": "Band_02",
      "central_frequency": {
        "value": 3.7,
        "unit": "µm"
      },
      "bandwidth": {
        "min": 3.55,
        "max": 3.85,
        "unit": "µm"
      },
      "SNR or NEΔT @ specified input": {
        "value": 0.08,
        "unit": "K @ 270 K"
      }
    },
    {
      "channel_name": "Band_03",
      "central_frequency": {
        "value": 10.85,
        "unit": "µm"
      },
      "bandwidth": {
        "min": 10.35,
        "max": 11.35,
        "unit": "µm"
      },
      "SNR or NEΔT @ specified input": {
        "value": 0.05,
        "unit": "K @ 270 K"
      }
    },
    {
      "channel_name": "Band_04",
      "central_frequency": {
        "value": 12.0,
        "unit": "µm"
      },
      "bandwidth": {
        "min": 11.5,
        "max": 12.5,
        "unit": "µm"
      },
      "SNR or NEΔT @ specified input": {
        "value": 0.05,
        "unit": "K @ 270 K"
      }
    },
    {
      "channel_name": "Band_05",
      "central_frequency": {
        "value": 23.8,
        "unit": "GHz"
      },
      "bandwidth": {
        "value": 400.0,
        "unit": "MHz"
      },
      "SNR or NEΔT @ specified input": {
        "value": 0.5,
        "unit": "K"
      }
    },
    {
      "channel_name": "Band_06",
      "central_frequency": {
        "value": 36.5,
        "unit": "GHz"
      },
      "bandwidth": {
        "value": 400.0,
        "unit": "MHz"
      },
      "SNR or NEΔT @ specified input": {
        "value": 0.5,
        "unit": "K"
      }
    }
  ]
}
