{
  "instrument_id": 1253,
  "instrument_acronym": "Capella SAR",
  "instrument_fullname": "Capella SAR",
  "url": "https://space.oscar.wmo.int/instruments/view/capella%20sar",
  "schema_type": "sar_active",
  "original_columns": [
    "Operation mode",
    "Resolution",
    "Swath",
    "Polarisation"
  ],
  "channels": [
    {
      "channel_name": "Band_01",
      "operation_mode": "Spotlight",
      "spatial_resolution": 0.3,
      "swath_width": 10000.0,
      "polarisation": "HH",
      "field_of_regard": null
    },
    {
      "channel_name": "Band_02",
      "operation_mode": "Sliding Spotlight",
      "spatial_resolution": 0.3,
      "swath_width": 20000.0,
      "polarisation": "HH",
      "field_of_regard": null
    },
    {
      "channel_name": "Band_03",
      "operation_mode": "Stripmap",
      "spatial_resolution": 0.3,
      "swath_width": 30000.0,
      "polarisation": "HH",
      "field_of_regard": null
    },
    {
      "channel_name": "Band_04",
      "operation_mode": "Multi-swath Stripmap",
      "spatial_resolution": 0.3,
      "swath_width": 50000.0,
      "polarisation": "HH",
      "field_of_regard": null
    }
  ]
}
